MistrasDTA/MistrasDTA.py
MistrasDTA/__init__.py
mistrasdta-0.1.6.dist-info/METADATA
mistrasdta-0.1.6.dist-info/WHEEL
mistrasdta-0.1.6.dist-info/licenses/LICENSE
mistrasdta-0.1.6.dist-info/RECORD
