Metadata-Version: 2.4
Name: MistrasDTA
Version: 0.1.6
Summary: Read AEWin acoustic emissions DTA files
Project-URL: Homepage, https://github.com/d-cogswell/MistrasDTA
Project-URL: Issues, https://github.com/d-cogswell/MistrasDTA/issues
Author-email: Dan Cogswell <cogswell@alum.mit.edu>
License-Expression: MIT
License-File: LICENSE
Classifier: Programming Language :: Python :: 3
Requires-Python: >=3.6
Requires-Dist: numpy
Provides-Extra: test
Requires-Dist: coveralls; extra == 'test'
Requires-Dist: pytest; extra == 'test'
